ghpdf/__init__.py
ghpdf/cli.py
ghpdf/converter.py
ghpdf/static/github.css
ghpdf-1.0.0.dist-info/METADATA
ghpdf-1.0.0.dist-info/WHEEL
ghpdf-1.0.0.dist-info/entry_points.txt
ghpdf-1.0.0.dist-info/RECORD
