Metadata-Version: 2.4
Name: ghpdf
Version: 1.0.0
Summary: Markdown to PDF converter with GitHub-style rendering
Project-URL: Homepage, https://github.com/atlekbai/md2pdf
Project-URL: Repository, https://github.com/atlekbai/md2pdf
Author: atlekbai
License: MIT
Keywords: cli,converter,markdown,pdf
Classifier: License :: OSI Approved :: MIT License
Classifier: Programming Language :: Python :: 3
Classifier: Programming Language :: Python :: 3.11
Classifier: Programming Language :: Python :: 3.12
Classifier: Topic :: Text Processing :: Markup :: Markdown
Requires-Python: >=3.11
Requires-Dist: markdown>=3.7
Requires-Dist: pygments>=2.18.0
Requires-Dist: typer>=0.12.0
Requires-Dist: weasyprint>=62.0
